typedal/__about__.py
typedal/__init__.py
typedal/caching.py
typedal/cli.py
typedal/config.py
typedal/constants.py
typedal/core.py
typedal/define.py
typedal/fields.py
typedal/for_py4web.py
typedal/for_web2py.py
typedal/helpers.py
typedal/mixins.py
typedal/py.typed
typedal/query_builder.py
typedal/relationships.py
typedal/rows.py
typedal/tables.py
typedal/types.py
typedal/web2py_py4web_shared.py
typedal/serializers/as_json.py
typedal-4.4.2.dist-info/METADATA
typedal-4.4.2.dist-info/WHEEL
typedal-4.4.2.dist-info/entry_points.txt
typedal-4.4.2.dist-info/RECORD
