Metadata-Version: 2.4
Name: TypeDAL
Version: 4.4.2
Summary: Typing support for PyDAL
Project-URL: Documentation, https://typedal.readthedocs.io/
Project-URL: Issues, https://github.com/trialandsuccess/TypeDAL/issues
Project-URL: Source, https://github.com/trialandsuccess/TypeDAL
Author-email: Robin van der Noord <contact@trialandsuccess.nl>
Classifier: Development Status :: 4 - Beta
Classifier: Programming Language :: Python
Classifier: Programming Language :: Python :: 3.11
Classifier: Programming Language :: Python :: 3.12
Classifier: Programming Language :: Python :: 3.13
Classifier: Programming Language :: Python :: 3.14
Classifier: Programming Language :: Python :: Implementation :: CPython
Classifier: Programming Language :: Python :: Implementation :: PyPy
Requires-Python: >=3.11
Requires-Dist: configurable-json<2
Requires-Dist: configuraptor<2,>=1.27.1
Requires-Dist: dill<1
Requires-Dist: legacy-cgi; python_version >= '3.13'
Requires-Dist: pydal>=20251012.3
Requires-Dist: python-dateutil<3
Requires-Dist: python-slugify<9
Provides-Extra: all
Requires-Dist: edwh-migrate[full]>=0.8.0; extra == 'all'
Requires-Dist: py4web; extra == 'all'
Requires-Dist: pydal2sql[all]>=1.2.0; extra == 'all'
Requires-Dist: questionary; extra == 'all'
Requires-Dist: tabulate; extra == 'all'
Requires-Dist: tomlkit; extra == 'all'
Requires-Dist: typer<0.19,>=0.18; extra == 'all'
Provides-Extra: dev
Requires-Dist: contextlib-chdir; extra == 'dev'
Requires-Dist: hatch; extra == 'dev'
Requires-Dist: mkdocs; extra == 'dev'
Requires-Dist: mkdocs-dracula-theme; extra == 'dev'
Requires-Dist: pytest-mypy-testing; extra == 'dev'
Requires-Dist: python-semantic-release<8; extra == 'dev'
Requires-Dist: requests<2.32; extra == 'dev'
Requires-Dist: su6[all]>=1.9.0; extra == 'dev'
Requires-Dist: testcontainers; extra == 'dev'
Requires-Dist: types-pyyaml; extra == 'dev'
Requires-Dist: types-requests; extra == 'dev'
Requires-Dist: types-tabulate; extra == 'dev'
Provides-Extra: migrations
Requires-Dist: edwh-migrate>=0.8.0; extra == 'migrations'
Requires-Dist: pydal2sql>=1.2.0; extra == 'migrations'
Requires-Dist: questionary; extra == 'migrations'
Requires-Dist: tabulate; extra == 'migrations'
Requires-Dist: tomlkit; extra == 'migrations'
Requires-Dist: typer<0.19,>=0.18; extra == 'migrations'
Provides-Extra: py4web
Requires-Dist: py4web; extra == 'py4web'
